termpixels/__init__.py
termpixels/app.py
termpixels/buffer.py
termpixels/color.py
termpixels/detector.py
termpixels/keys.py
termpixels/observable.py
termpixels/pixeldata.py
termpixels/screen.py
termpixels/terminfo.py
termpixels/unix.py
termpixels/unix_keys.py
termpixels/util.py
termpixels/win32.py
termpixels/win32_keys.py
termpixels-0.0.11.dist-info/LICENSE
termpixels-0.0.11.dist-info/METADATA
termpixels-0.0.11.dist-info/WHEEL
termpixels-0.0.11.dist-info/top_level.txt
termpixels-0.0.11.dist-info/RECORD
