Metadata-Version: 2.1
Name: termpixels
Version: 0.0.11
Summary: Terminal I/O with a pixel-like abstraction
Home-page: https://github.com/loganzartman/termpixels
Author: Logan
Author-email: logan.zartman@utexas.edu
License: UNKNOWN
Platform: UNKNOWN
Classifier: Programming Language :: Python :: 3
Classifier: License :: OSI Approved :: MIT License
Classifier: Operating System :: OS Independent
